meme_generator_contrib-0.2.0a6.dist-info/METADATA
meme_generator_contrib-0.2.0a6.dist-info/WHEEL
meme_generator/__init__.py
meme_generator/__init__.pyi
meme_generator/py.typed
meme_generator/meme_generator.pyd
meme_generator_contrib-0.2.0a6.dist-info/RECORD
